cds_trytond_cms-4.6.2.dist-info/DESCRIPTION.rst
cds_trytond_cms-4.6.2.dist-info/METADATA
cds_trytond_cms-4.6.2.dist-info/RECORD
cds_trytond_cms-4.6.2.dist-info/WHEEL
cds_trytond_cms-4.6.2.dist-info/entry_points.txt
cds_trytond_cms-4.6.2.dist-info/metadata.json
cds_trytond_cms-4.6.2.dist-info/top_level.txt
trytond/modules/cms/__init__.py
trytond/modules/cms/cms.py
trytond/modules/cms/cms.xml
trytond/modules/cms/tryton.cfg
trytond/modules/cms/view/cms_article_form.xml
trytond/modules/cms/view/cms_article_list.xml
trytond/modules/cms/view/cms_article_tree.xml
